[
  {
    "Id": "43049689-caf5-4acd-83e7-6e4a0fb78959",
    "Title": "hello",
    "IsCompleted": false,
    "CreatedAt": "2026-01-21T22:04:04.5608103+05:30",
    "DueDate": "2026-01-22T00:00:00",
    "Priority": "Medium",
    "UserId": 1
  },
  {
    "Id": "20ac3d81-b74f-4898-8d03-294a07bacc80",
    "Title": "hello",
    "IsCompleted": false,
    "CreatedAt": "2026-01-21T22:04:33.5144431+05:30",
    "DueDate": null,
    "Priority": "Medium",
    "UserId": 1
  },
  {
    "Id": "434b08c0-17d8-428c-9fff-3f006ea0f12d",
    "Title": "hello",
    "IsCompleted": false,
    "CreatedAt": "2026-01-21T22:04:49.7025797+05:30",
    "DueDate": null,
    "Priority": "Medium",
    "UserId": 1
  },
  {
    "Id": "4214f69c-0cef-4a0f-a40e-b1f769ff7079",
    "Title": "hello",
    "IsCompleted": false,
    "CreatedAt": "2026-01-21T22:05:30.5640466+05:30",
    "DueDate": null,
    "Priority": "Medium",
    "UserId": 1
  },
  {
    "Id": "bbc4927c-9221-499f-b63a-1b59102ce1c7",
    "Title": "hello",
    "IsCompleted": false,
    "CreatedAt": "2026-01-23T11:13:51.2074159+05:30",
    "DueDate": null,
    "Priority": "Medium",
    "UserId": 1
  },
  {
    "Id": "4b9e399c-0821-4e0c-b028-d687ce914903",
    "Title": "hello",
    "IsCompleted": false,
    "CreatedAt": "2026-01-23T11:44:13.9203858+05:30",
    "DueDate": null,
    "Priority": "Medium",
    "UserId": 1
  },
  {
    "Id": "b4d00b55-2c0b-4da3-b32c-c651d9522faa",
    "Title": "hi what are you doing ",
    "IsCompleted": false,
    "CreatedAt": "2026-01-23T17:36:29.7489334+05:30",
    "DueDate": null,
    "Priority": "Medium",
    "UserId": 1
  },
  {
    "Id": "cc477796-13b3-4a3c-b6d6-7c6bf4bcc781",
    "Title": "hi",
    "IsCompleted": false,
    "CreatedAt": "2026-01-23T17:36:41.3674439+05:30",
    "DueDate": null,
    "Priority": "Medium",
    "UserId": 1
  },
  {
    "Id": "aabfaf8e-8ac2-4e54-9eff-d945db56ce05",
    "Title": "hi, what are you doing ",
    "IsCompleted": false,
    "CreatedAt": "2026-01-23T17:36:55.859704+05:30",
    "DueDate": null,
    "Priority": "Medium",
    "UserId": 1
  },
  {
    "Id": "2615b0c2-03b7-4ef0-a753-bb0c7dd066e3",
    "Title": "what are you doing",
    "IsCompleted": false,
    "CreatedAt": "2026-01-23T17:37:14.825676+05:30",
    "DueDate": null,
    "Priority": "Medium",
    "UserId": 1
  },
  {
    "Id": "299bc920-97e2-46fe-b8a5-61fd1a2b754a",
    "Title": "ticking",
    "IsCompleted": false,
    "CreatedAt": "2026-01-23T17:42:32.0489644+05:30",
    "DueDate": null,
    "Priority": "Medium",
    "UserId": 1
  },
  {
    "Id": "3e83250f-c982-4f2c-8b10-102aeab80517",
    "Title": "blinking",
    "IsCompleted": false,
    "CreatedAt": "2026-01-23T17:43:24.6045408+05:30",
    "DueDate": null,
    "Priority": "Medium",
    "UserId": 1
  }
]